C45/__init__.py
c45_decision_tree-1.0.1.dist-info/METADATA
c45_decision_tree-1.0.1.dist-info/WHEEL
c45_decision_tree-1.0.1.dist-info/top_level.txt
c45_decision_tree-1.0.1.dist-info/RECORD
