Metadata-Version: 2.1
Name: c45-decision-tree
Version: 1.0.1
Summary: Library for C4.5 Decision Tree Algorithm
Home-page: https://github.com/novandikp/DecisionTreeC45
Author: Novandi Kevin Pratama
Author-email: kevinpret27@gmail.com
Classifier: Programming Language :: Python :: 3
Classifier: License :: OSI Approved :: MIT License
Classifier: Operating System :: OS Independent
